QuantumArtLibrary/QuantumArtLibrary.py
QuantumArtLibrary/__init__.py
QuantumArtLibrary/_version.py
QuantumArtLibrary/gl_util.py
QuantumArtLibrary-1.0.0.dist-info/LICENSE
QuantumArtLibrary-1.0.0.dist-info/METADATA
QuantumArtLibrary-1.0.0.dist-info/WHEEL
QuantumArtLibrary-1.0.0.dist-info/top_level.txt
QuantumArtLibrary-1.0.0.dist-info/RECORD
