Metadata-Version: 2.1
Name: QuantumArtLibrary
Version: 1.0.0
Summary: Creative coding library for artistic expression of quantum behavior.
Home-page: https://github.com/taikiwakatsuki/Quantum-Art-Library
Author: taikiwakatsuki
Author-email: mutual_bookers.0q@icloud.com
Classifier: Programming Language :: Python :: 3.7
Classifier: Programming Language :: Python :: 3.8
Classifier: License :: OSI Approved :: BSD License
Classifier: Operating System :: OS Independent
License-File: LICENSE
Requires-Dist: numpy
Requires-Dist: matplotlib
Requires-Dist: tqdm
Requires-Dist: PyOpenGL
Requires-Dist: glfw
Requires-Dist: opencv-python
Requires-Dist: Pillow
